argalias/__about__.py
argalias/__init__.py
argalias-1.0.1.dist-info/METADATA
argalias-1.0.1.dist-info/WHEEL
argalias-1.0.1.dist-info/licenses/LICENSE
argalias-1.0.1.dist-info/RECORD
