Metadata-Version: 2.4
Name: argalias
Version: 1.0.1
Summary: Argument aliases/abbrevations for CLI programs (compatible with argparse/click/typer/...)
Project-URL: Documentation, https://github.com/yaroslaff/argalias#readme
Project-URL: Issues, https://github.com/yaroslaff/argalias/issues
Project-URL: Source, https://github.com/yaroslaff/argalias
Author-email: Yaroslav Polyakov <yaroslaff@gmail.com>
License-Expression: MIT
License-File: LICENSE
Classifier: Development Status :: 4 - Beta
Classifier: Programming Language :: Python
Classifier: Programming Language :: Python :: 3.7
Classifier: Programming Language :: Python :: 3.8
Classifier: Programming Language :: Python :: 3.9
Classifier: Programming Language :: Python :: 3.10
Classifier: Programming Language :: Python :: 3.11
Classifier: Programming Language :: Python :: Implementation :: CPython
Classifier: Programming Language :: Python :: Implementation :: PyPy
Requires-Python: >=3.7
